{
    "data": [
        {
            "title": "EM",
            "subtitle": "VES USD",
            "rate": "255,38",
            "change": "+0,69%",
            "date": "05-10-2025 08:20 pm",
            "image_url": "https://exchangemonitor.net/assets/img/rates/ve/em.webp"
        },
        {
            "title": "Monitor D\u00f3lar",
            "subtitle": "VES USD",
            "rate": "255,38",
            "change": "+0,69%",
            "date": "05-10-2025 08:20 pm",
            "image_url": "https://exchangemonitor.net/assets/img/rates/ve/md.png"
        },
        {
            "title": "Promedio",
            "subtitle": "VES USD",
            "rate": "221,93",
            "change": "-0,30%",
            "date": "03-10-2025 10:00 pm",
            "image_url": "https://exchangemonitor.net/assets/img/rates/ve/average-v2.png"
        },
        {
            "title": "BCV",
            "subtitle": "VES USD",
            "rate": "185,40",
            "change": "0,00%",
            "date": "03-10-2025 09:40 pm",
            "image_url": "https://exchangemonitor.net/assets/img/rates/ve/bcv.png"
        },
        {
            "title": "Binance",
            "subtitle": "VES USD",
            "rate": "290,98",
            "change": "+1,21%",
            "date": "05-10-2025 08:20 pm",
            "image_url": "https://exchangemonitor.net/assets/img/rates/ve/binance.png"
        },
        {
            "title": "Yadio",
            "subtitle": "VES USD",
            "rate": "289,94",
            "change": "+1,36%",
            "date": "05-10-2025 08:20 pm",
            "image_url": "https://exchangemonitor.net/assets/img/rates/ve/yadio.png"
        },
        {
            "title": "Bancamiga",
            "subtitle": "VES USD",
            "rate": "181,77",
            "change": "+2,95%",
            "date": "03-10-2025 09:40 pm",
            "image_url": "https://exchangemonitor.net/assets/img/rates/ve/bank-bancamiga.png"
        },
        {
            "title": "BanCaribe",
            "subtitle": "VES USD",
            "rate": "168,42",
            "change": "0,00%",
            "date": "23-09-2025 09:40 pm",
            "image_url": "https://exchangemonitor.net/assets/img/rates/ve/bank-bancaribe.png"
        },
        {
            "title": "Banco Activo",
            "subtitle": "VES USD",
            "rate": "184,32",
            "change": "0,00%",
            "date": "02-10-2025 09:40 pm",
            "image_url": "https://exchangemonitor.net/assets/img/rates/ve/bank-activo.png"
        },
        {
            "title": "Banco Exterior",
            "subtitle": "VES USD",
            "rate": "155,86",
            "change": "0,00%",
            "date": "05-09-2025 09:40 pm",
            "image_url": "https://exchangemonitor.net/assets/img/rates/ve/bank-exterior.png"
        },
        {
            "title": "Banco Mercantil",
            "subtitle": "VES USD",
            "rate": "186,07",
            "change": "-5,93%",
            "date": "03-10-2025 09:40 pm",
            "image_url": "https://exchangemonitor.net/assets/img/rates/ve/bank-mercantil.png"
        },
        {
            "title": "Banco Plaza",
            "subtitle": "VES USD",
            "rate": "175,00",
            "change": "0,00%",
            "date": "29-09-2025 09:40 pm",
            "image_url": "https://exchangemonitor.net/assets/img/rates/ve/bank-plaza.png"
        },
        {
            "title": "Banco Provincial",
            "subtitle": "VES USD",
            "rate": "185,62",
            "change": "-0,74%",
            "date": "03-10-2025 09:40 pm",
            "image_url": "https://exchangemonitor.net/assets/img/rates/ve/bank-provincial.png"
        },
        {
            "title": "Banesco",
            "subtitle": "VES USD",
            "rate": "185,80",
            "change": "-2,43%",
            "date": "03-10-2025 09:40 pm",
            "image_url": "https://exchangemonitor.net/assets/img/rates/ve/bank-banesco.png"
        },
        {
            "title": "Bangente",
            "subtitle": "VES USD",
            "rate": "166,00",
            "change": "0,00%",
            "date": "19-09-2025 09:40 pm",
            "image_url": "https://exchangemonitor.net/assets/img/rates/ve/bank-bangente.png"
        },
        {
            "title": "BDV",
            "subtitle": "VES USD",
            "rate": "175,65",
            "change": "0,00%",
            "date": "29-09-2025 09:40 pm",
            "image_url": "https://exchangemonitor.net/assets/img/rates/ve/bank-bdv.png"
        },
        {
            "title": "BNC",
            "subtitle": "VES USD",
            "rate": "187,52",
            "change": "-0,76%",
            "date": "03-10-2025 09:40 pm",
            "image_url": "https://exchangemonitor.net/assets/img/rates/ve/bank-bnc.png"
        },
        {
            "title": "Otras Instituciones",
            "subtitle": "VES USD",
            "rate": "186,40",
            "change": "-2,29%",
            "date": "03-10-2025 09:40 pm",
            "image_url": "https://exchangemonitor.net/assets/img/rates/ve/bank-instituciones.png"
        }
    ],
    "updated_at": "2025-10-05 16:23:00"
}